account-service_client/__init__.py
account-service_client/api_client.py
account-service_client/api_response.py
account-service_client/configuration.py
account-service_client/exceptions.py
account-service_client/py.typed
account-service_client/rest.py
account-service_client/api/__init__.py
account-service_client/api/account_api.py
account-service_client/api/default_api.py
account-service_client/models/__init__.py
account-service_client/models/profile_put_request.py
account-service_client/models/settings.py
account-service_client/models/user_profile.py
test/__init__.py
test/test_account_api.py
test/test_default_api.py
test/test_profile_put_request.py
test/test_settings.py
test/test_user_profile.py
hosting_platform_account_client-1.0.0.dist-info/METADATA
hosting_platform_account_client-1.0.0.dist-info/WHEEL
hosting_platform_account_client-1.0.0.dist-info/top_level.txt
hosting_platform_account_client-1.0.0.dist-info/RECORD
