Metadata-Version: 2.4
Name: hosting-platform-account-client
Version: 1.0.0
Summary: Python client for account-service API (Proprietary)
Home-page: 
Author: OpenAPI Generator community
Author-email: Free Hosting Platform Team <support@platform.dev>
License: Proprietary
Project-URL: Homepage, https://github.com/PotashAlum/Hostopia
Project-URL: Repository, https://github.com/PotashAlum/Hostopia
Project-URL: Issues, https://github.com/PotashAlum/Hostopia/issues
Keywords: hosting,api,client,account,private
Classifier: Development Status :: 4 - Beta
Classifier: Intended Audience :: Developers
Classifier: License :: Other/Proprietary License
Classifier: Programming Language :: Python :: 3
Classifier: Programming Language :: Python :: 3.8
Classifier: Programming Language :: Python :: 3.9
Classifier: Programming Language :: Python :: 3.10
Classifier: Programming Language :: Python :: 3.11
Requires-Python: >=3.8
Requires-Dist: urllib3>=1.25.3
Requires-Dist: python-dateutil
Requires-Dist: pydantic>=1.10.5
Requires-Dist: typing-extensions>=4.0.0
Dynamic: author
